ihi_primenumber/__init__.py
ihi_primenumber/code.py
ihi_primenumber-1.0.1.dist-info/LICENSE
ihi_primenumber-1.0.1.dist-info/METADATA
ihi_primenumber-1.0.1.dist-info/WHEEL
ihi_primenumber-1.0.1.dist-info/top_level.txt
ihi_primenumber-1.0.1.dist-info/RECORD
