Metadata-Version: 2.1
Name: ihi-primenumber
Version: 1.0.1
Summary: For Prime Number
Home-page: UNKNOWN
Author: Shakeel Abbas (imam Hussain a.s institute)
Author-email: <ihi.karachi@gmail.com>
License: UNKNOWN
Keywords: python,primenumber,math
Platform: UNKNOWN
Classifier: Development Status :: 1 - Planning
Classifier: Intended Audience :: Developers
Classifier: Programming Language :: Python :: 3
Classifier: Operating System :: Unix
Classifier: Operating System :: MacOS :: MacOS X
Classifier: Operating System :: Microsoft :: Windows
